cyborg/__init__.py
cyborg/context.py
cyborg/quota.py
cyborg/service_auth.py
cyborg/version.py
cyborg/accelerator/__init__.py
cyborg/accelerator/accelerator.py
cyborg/accelerator/configuration.py
cyborg/accelerator/common/__init__.py
cyborg/accelerator/common/exception.py
cyborg/accelerator/common/utils.py
cyborg/accelerator/drivers/__init__.py
cyborg/accelerator/drivers/driver.py
cyborg/accelerator/drivers/fake.py
cyborg/accelerator/drivers/aichip/__init__.py
cyborg/accelerator/drivers/aichip/huawei/__init__.py
cyborg/accelerator/drivers/aichip/huawei/ascend.py
cyborg/accelerator/drivers/fpga/__init__.py
cyborg/accelerator/drivers/fpga/base.py
cyborg/accelerator/drivers/fpga/utils.py
cyborg/accelerator/drivers/fpga/inspur/__init__.py
cyborg/accelerator/drivers/fpga/inspur/driver.py
cyborg/accelerator/drivers/fpga/inspur/sysinfo.py
cyborg/accelerator/drivers/fpga/intel/__init__.py
cyborg/accelerator/drivers/fpga/intel/driver.py
cyborg/accelerator/drivers/fpga/intel/sysinfo.py
cyborg/accelerator/drivers/fpga/xilinx/__init__.py
cyborg/accelerator/drivers/fpga/xilinx/driver.py
cyborg/accelerator/drivers/fpga/xilinx/sysinfo.py
cyborg/accelerator/drivers/gpu/__init__.py
cyborg/accelerator/drivers/gpu/base.py
cyborg/accelerator/drivers/gpu/utils.py
cyborg/accelerator/drivers/gpu/nvidia/__init__.py
cyborg/accelerator/drivers/gpu/nvidia/driver.py
cyborg/accelerator/drivers/gpu/nvidia/sysinfo.py
cyborg/accelerator/drivers/modules/__init__.py
cyborg/accelerator/drivers/modules/generic.py
cyborg/accelerator/drivers/nic/__init__.py
cyborg/accelerator/drivers/nic/base.py
cyborg/accelerator/drivers/nic/intel/__init__.py
cyborg/accelerator/drivers/nic/intel/driver.py
cyborg/accelerator/drivers/nic/intel/sysinfo.py
cyborg/accelerator/drivers/pci/__init__.py
cyborg/accelerator/drivers/pci/base.py
cyborg/accelerator/drivers/pci/devspec.py
cyborg/accelerator/drivers/pci/utils.py
cyborg/accelerator/drivers/pci/whitelist.py
cyborg/accelerator/drivers/pci/pci/__init__.py
openstack_cyborg-15.0.0.dist-info/AUTHORS
openstack_cyborg-15.0.0.dist-info/LICENSE
openstack_cyborg-15.0.0.dist-info/METADATA
openstack_cyborg-15.0.0.dist-info/WHEEL
openstack_cyborg-15.0.0.dist-info/entry_points.txt
openstack_cyborg-15.0.0.dist-info/pbr.json
openstack_cyborg-15.0.0.dist-info/top_level.txt
openstack_cyborg-15.0.0.dist-info/RECORD
